giford/__init__.py
giford/_version.py
giford/action/__init__.py
giford/action/abstract_action.py
giford/action/abstract_frame_action.py
giford/action/crop.py
giford/action/reshape.py
giford/action/rotate.py
giford/action/scroll.py
giford/action/shake.py
giford/action/swirl.py
giford/action/translate.py
giford/action/zoom.py
giford/frame/__init__.py
giford/frame/frame_batch.py
giford/frame/raw_data.py
giford/image/__init__.py
giford/image/abstract_image.py
giford/image/multi_image.py
giford/image/single_image.py
giford/util/__init__.py
giford/util/io_util.py
giford/util/virtual_path.py
giford-0.6.0.dist-info/LICENSE.txt
giford-0.6.0.dist-info/METADATA
giford-0.6.0.dist-info/WHEEL
giford-0.6.0.dist-info/top_level.txt
giford-0.6.0.dist-info/RECORD
