Metadata-Version: 2.1
Name: giford
Version: 0.6.0
Summary: easy image and gif manipulation
Author: Alex Harding
License: MIT License
Project-URL: homepage, https://github.com/whale-net/giford
Project-URL: repository, https://github.com/whale-net/giford.git
Requires-Python: >=3.10
License-File: LICENSE.txt
Requires-Dist: numpy
Requires-Dist: scikit-image
Requires-Dist: ffmpeg-python
Requires-Dist: setuptools
Requires-Dist: setuptools-scm
Requires-Dist: Pillow
Provides-Extra: dev
Requires-Dist: giford[test] ; extra == 'dev'
Requires-Dist: giford[lint] ; extra == 'dev'
Provides-Extra: lint
Requires-Dist: black ; extra == 'lint'
Requires-Dist: giford[mypy] ; extra == 'lint'
Requires-Dist: pylint ; extra == 'lint'
Provides-Extra: mypy
Requires-Dist: mypy ; extra == 'mypy'
Requires-Dist: types-Pillow ; extra == 'mypy'
Provides-Extra: test
Requires-Dist: pytest ; extra == 'test'
Requires-Dist: pytest-xdist ; extra == 'test'
Requires-Dist: pytest-cov ; extra == 'test'
